redfin_houses/__init__.py
redfin_houses/house_filter.py
redfin_houses/redfin.py
redfin_houses-0.0.3.dist-info/DESCRIPTION.rst
redfin_houses-0.0.3.dist-info/METADATA
redfin_houses-0.0.3.dist-info/RECORD
redfin_houses-0.0.3.dist-info/WHEEL
redfin_houses-0.0.3.dist-info/metadata.json
redfin_houses-0.0.3.dist-info/top_level.txt
